dora_arm_piper/main.py
dora_arm_piper/read_data.py
dora_arm_piper-0.0.5.dist-info/licenses/LICENSE
dora_arm_piper-0.0.5.dist-info/METADATA
dora_arm_piper-0.0.5.dist-info/WHEEL
dora_arm_piper-0.0.5.dist-info/entry_points.txt
dora_arm_piper-0.0.5.dist-info/top_level.txt
dora_arm_piper-0.0.5.dist-info/RECORD
