Metadata-Version: 2.4
Name: dora-arm-piper
Version: 0.0.5
Author-email: Xiang Yang <ryu-yang@qq.com>
Requires-Python: <3.14,>=3.8
License-File: LICENSE
Requires-Dist: dora-rs<0.4.0,>=0.3.11
Requires-Dist: piper_sdk>=0.0.8
Requires-Dist: numpy>=1.24.4
Provides-Extra: view
Requires-Dist: dora-rs-cli; extra == "view"
Requires-Dist: dora-rerun; extra == "view"
Dynamic: license-file
